site_block/__init__.py
site_block-0.0.1.dist-info/METADATA
site_block-0.0.1.dist-info/WHEEL
site_block-0.0.1.dist-info/entry_points.txt
site_block-0.0.1.dist-info/top_level.txt
site_block-0.0.1.dist-info/RECORD
